{"mygraph":{"nodes":[66,56,104,76],"index":8,"links":[320,167,199,203,204,364,205,237,206,208,241,242,243,275,244,246,279,280,281,282,284]},"myrank":8,"neighbors":[{"rank":6,"rel_sinks":[206],"rel_sources":[167]},{"rank":11,"rel_sinks":[242],"rel_sources":[237]},{"rank":12,"rel_sinks":[203,241],"rel_sources":[208,246]},{"rank":14,"rel_sinks":[279],"rel_sources":[284]},{"rank":15,"rel_sinks":[281],"rel_sources":[320]},{"rank":23,"rel_sinks":[280],"rel_sources":[275]},{"rank":24,"rel_sinks":[204],"rel_sources":[199]}]}